Metadata-Version: 1.0
Name: timestamp-snail
Version: 1.0.0
Summary: 在终端对日期和时间进行相关操作
Home-page: https://github.com/champion-yang
Author: Junlin Yang
Author-email: snail.yang@foxmail.com
License: UNKNOWN
Platform: UNKNOWN
